factrainer/lightgbm/__init__.py
factrainer/lightgbm/config.py
factrainer/lightgbm/py.typed
factrainer/lightgbm/raw_model.py
factrainer/lightgbm/dataset/__init__.py
factrainer/lightgbm/dataset/dataset.py
factrainer/lightgbm/dataset/slicer.py
factrainer/lightgbm/dataset/types.py
factrainer_lightgbm-0.1.27.dist-info/METADATA
factrainer_lightgbm-0.1.27.dist-info/WHEEL
factrainer_lightgbm-0.1.27.dist-info/RECORD
